{"Transform":{"Matrix":{"Components":[1.0,0.0,0.0,0.0,0.0,1.0,0.0,0.0,0.0,0.0,1.0,0.0]}},"Elements":{"9babb829-9b96-4e73-97f4-9658d4d6c31c":{"discriminator":"Elements.Material","Color":{"Red":1.0,"Green":1.0,"Blue":1.0,"Alpha":1.0},"SpecularFactor":0.0,"GlossinessFactor":0.0,"Unlit":false,"DoubleSided":false,"Id":"9babb829-9b96-4e73-97f4-9658d4d6c31c","Name":"default"},"6a7f1ed9-0b2d-47de-8425-9948d060d2ef":{"discriminator":"Elements.MeshElement","Transform":{"Matrix":{"Components":[1.0,0.0,0.0,0.0,0.0,1.0,0.0,0.0,0.0,0.0,1.0,0.0]}},"Material":"9babb829-9b96-4e73-97f4-9658d4d6c31c","Representation":null,"IsElementDefinition":false,"Id":"6a7f1ed9-0b2d-47de-8425-9948d060d2ef","Name":null},"1c49f0e8-b206-4ba8-b72e-092a4b51e774":{"discriminator":"Elements.MeshElement","Transform":{"Matrix":{"Components":[1.0,0.0,0.0,0.0,0.0,1.0,0.0,0.0,0.0,0.0,1.0,0.0]}},"Material":"9babb829-9b96-4e73-97f4-9658d4d6c31c","Representation":null,"IsElementDefinition":false,"Id":"1c49f0e8-b206-4ba8-b72e-092a4b51e774","Name":null},"10e823d0-a03e-4863-87e8-22146275ea0b":{"discriminator":"Elements.MeshElement","Transform":{"Matrix":{"Components":[1.0,0.0,0.0,0.0,0.0,1.0,0.0,0.0,0.0,0.0,1.0,0.0]}},"Material":"9babb829-9b96-4e73-97f4-9658d4d6c31c","Representation":null,"IsElementDefinition":false,"Id":"10e823d0-a03e-4863-87e8-22146275ea0b","Name":null},"7298d643-9049-4a2b-960d-ae775b50fd80":{"discriminator":"Elements.Material","Color":{"Red":0.0,"Green":0.0,"Blue":0.0,"Alpha":1.0},"SpecularFactor":0.0,"GlossinessFactor":0.0,"Unlit":false,"DoubleSided":false,"Id":"7298d643-9049-4a2b-960d-ae775b50fd80","Name":"black"},"07cd4e72-d669-4648-b681-cc6ee125ac5f":{"discriminator":"Elements.Roof","Envelope":{"discriminator":"Mesh","Vertices":[],"Triangles":[],"Material":"9babb829-9b96-4e73-97f4-9658d4d6c31c"},"Topside":{"discriminator":"Mesh","Vertices":[{"discriminator":"Elements.Geometry.Solids.Vertex","Position":{"X":-8.3650963499731166,"Y":-25.973472041564793,"Z":0.39028878197218669},"Normal":{"X":0.0,"Y":0.0,"Z":1.0},"Color":{"Red":0.0,"Green":0.0,"Blue":0.0,"Alpha":0.0},"Index":0,"UV":{"discriminator":"Elements.Geometry.UV","U":0.0,"V":0.0},"Id":0,"HalfEdge":null,"Point":{"X":0.0,"Y":0.0,"Z":0.0}},{"discriminator":"Elements.Geometry.Solids.Vertex","Position":{"X":-2.465096349973078,"Y":-20.0734720415648,"Z":0.39028878197218669},"Normal":{"X":0.0,"Y":0.0,"Z":1.0},"Color":{"Red":0.0,"Green":0.0,"Blue":0.0,"Alpha":0.0},"Index":1,"UV":{"discriminator":"Elements.Geometry.UV","U":0.0,"V":0.0},"Id":0,"HalfEdge":null,"Point":{"X":0.0,"Y":0.0,"Z":0.0}},{"discriminator":"Elements.Geometry.Solids.Vertex","Position":{"X":-9.66509634997303,"Y":-25.973472041564793,"Z":0.39028878197218669},"Normal":{"X":0.0,"Y":0.0,"Z":1.0},"Color":{"Red":0.0,"Green":0.0,"Blue":0.0,"Alpha":0.0},"Index":2,"UV":{"discriminator":"Elements.Geometry.UV","U":0.0,"V":0.0},"Id":0,"HalfEdge":null,"Point":{"X":0.0,"Y":0.0,"Z":0.0}},{"discriminator":"Elements.Geometry.Solids.Vertex","Position":{"X":-2.465096349973078,"Y":-20.0734720415648,"Z":0.39028878197218669},"Normal":{"X":0.0,"Y":0.0,"Z":1.0},"Color":{"Red":0.0,"Green":0.0,"Blue":0.0,"Alpha":0.0},"Index":3,"UV":{"discriminator":"Elements.Geometry.UV","U":0.0,"V":0.0},"Id":0,"HalfEdge":null,"Point":{"X":0.0,"Y":0.0,"Z":0.0}},{"discriminator":"Elements.Geometry.Solids.Vertex","Position":{"X":-15.56509634997308,"Y":-20.0734720415648,"Z":0.39028878197218669},"Normal":{"X":0.0,"Y":0.0,"Z":1.0},"Color":{"Red":0.0,"Green":0.0,"Blue":0.0,"Alpha":0.0},"Index":4,"UV":{"discriminator":"Elements.Geometry.UV","U":0.0,"V":0.0},"Id":0,"HalfEdge":null,"Point":{"X":0.0,"Y":0.0,"Z":0.0}},{"discriminator":"Elements.Geometry.Solids.Vertex","Position":{"X":-9.66509634997303,"Y":-25.973472041564793,"Z":0.39028878197218669},"Normal":{"X":0.0,"Y":0.0,"Z":1.0},"Color":{"Red":0.0,"Green":0.0,"Blue":0.0,"Alpha":0.0},"Index":5,"UV":{"discriminator":"Elements.Geometry.UV","U":0.0,"V":0.0},"Id":0,"HalfEdge":null,"Point":{"X":0.0,"Y":0.0,"Z":0.0}},{"discriminator":"Elements.Geometry.Solids.Vertex","Position":{"X":-2.465096349973078,"Y":-31.8734720415648,"Z":0.39028878197218697},"Normal":{"X":0.0,"Y":0.0,"Z":1.0},"Color":{"Red":0.0,"Green":0.0,"Blue":0.0,"Alpha":0.0},"Index":6,"UV":{"discriminator":"Elements.Geometry.UV","U":0.0,"V":0.0},"Id":0,"HalfEdge":null,"Point":{"X":0.0,"Y":0.0,"Z":0.0}},{"discriminator":"Elements.Geometry.Solids.Vertex","Position":{"X":-2.465096349973078,"Y":-20.0734720415648,"Z":0.39028878197218697},"Normal":{"X":0.0,"Y":0.0,"Z":1.0},"Color":{"Red":0.0,"Green":0.0,"Blue":0.0,"Alpha":0.0},"Index":7,"UV":{"discriminator":"Elements.Geometry.UV","U":0.0,"V":0.0},"Id":0,"HalfEdge":null,"Point":{"X":0.0,"Y":0.0,"Z":0.0}},{"discriminator":"Elements.Geometry.Solids.Vertex","Position":{"X":-8.3650963499731166,"Y":-25.973472041564793,"Z":0.39028878197218697},"Normal":{"X":0.0,"Y":0.0,"Z":1.0},"Color":{"Red":0.0,"Green":0.0,"Blue":0.0,"Alpha":0.0},"Index":8,"UV":{"discriminator":"Elements.Geometry.UV","U":0.0,"V":0.0},"Id":0,"HalfEdge":null,"Point":{"X":0.0,"Y":0.0,"Z":0.0}},{"discriminator":"Elements.Geometry.Solids.Vertex","Position":{"X":-2.465096349973078,"Y":-31.8734720415648,"Z":0.39028878197218697},"Normal":{"X":0.0,"Y":0.0,"Z":1.0},"Color":{"Red":0.0,"Green":0.0,"Blue":0.0,"Alpha":0.0},"Index":9,"UV":{"discriminator":"Elements.Geometry.UV","U":0.0,"V":0.0},"Id":0,"HalfEdge":null,"Point":{"X":0.0,"Y":0.0,"Z":0.0}},{"discriminator":"Elements.Geometry.Solids.Vertex","Position":{"X":-8.3650963499731166,"Y":-25.973472041564793,"Z":0.39028878197218697},"Normal":{"X":0.0,"Y":0.0,"Z":1.0},"Color":{"Red":0.0,"Green":0.0,"Blue":0.0,"Alpha":0.0},"Index":10,"UV":{"discriminator":"Elements.Geometry.UV","U":0.0,"V":0.0},"Id":0,"HalfEdge":null,"Point":{"X":0.0,"Y":0.0,"Z":0.0}},{"discriminator":"Elements.Geometry.Solids.Vertex","Position":{"X":-9.66509634997303,"Y":-25.973472041564793,"Z":0.39028878197218697},"Normal":{"X":0.0,"Y":0.0,"Z":1.0},"Color":{"Red":0.0,"Green":0.0,"Blue":0.0,"Alpha":0.0},"Index":11,"UV":{"discriminator":"Elements.Geometry.UV","U":0.0,"V":0.0},"Id":0,"HalfEdge":null,"Point":{"X":0.0,"Y":0.0,"Z":0.0}},{"discriminator":"Elements.Geometry.Solids.Vertex","Position":{"X":-9.66509634997303,"Y":-25.973472041564793,"Z":0.39028878197218697},"Normal":{"X":0.0,"Y":0.0,"Z":1.0},"Color":{"Red":0.0,"Green":0.0,"Blue":0.0,"Alpha":0.0},"Index":12,"UV":{"discriminator":"Elements.Geometry.UV","U":0.0,"V":0.0},"Id":0,"HalfEdge":null,"Point":{"X":0.0,"Y":0.0,"Z":0.0}},{"discriminator":"Elements.Geometry.Solids.Vertex","Position":{"X":-15.56509634997308,"Y":-31.8734720415648,"Z":0.39028878197218697},"Normal":{"X":0.0,"Y":0.0,"Z":1.0},"Color":{"Red":0.0,"Green":0.0,"Blue":0.0,"Alpha":0.0},"Index":13,"UV":{"discriminator":"Elements.Geometry.UV","U":0.0,"V":0.0},"Id":0,"HalfEdge":null,"Point":{"X":0.0,"Y":0.0,"Z":0.0}},{"discriminator":"Elements.Geometry.Solids.Vertex","Position":{"X":-2.465096349973078,"Y":-31.8734720415648,"Z":0.39028878197218697},"Normal":{"X":0.0,"Y":0.0,"Z":1.0},"Color":{"Red":0.0,"Green":0.0,"Blue":0.0,"Alpha":0.0},"Index":14,"UV":{"discriminator":"Elements.Geometry.UV","U":0.0,"V":0.0},"Id":0,"HalfEdge":null,"Point":{"X":0.0,"Y":0.0,"Z":0.0}},{"discriminator":"Elements.Geometry.Solids.Vertex","Position":{"X":-15.56509634997308,"Y":-20.0734720415648,"Z":0.39028878197218697},"Normal":{"X":0.0,"Y":0.0,"Z":1.0},"Color":{"Red":0.0,"Green":0.0,"Blue":0.0,"Alpha":0.0},"Index":15,"UV":{"discriminator":"Elements.Geometry.UV","U":0.0,"V":0.0},"Id":0,"HalfEdge":null,"Point":{"X":0.0,"Y":0.0,"Z":0.0}},{"discriminator":"Elements.Geometry.Solids.Vertex","Position":{"X":-15.56509634997308,"Y":-31.8734720415648,"Z":0.39028878197218697},"Normal":{"X":0.0,"Y":0.0,"Z":1.0},"Color":{"Red":0.0,"Green":0.0,"Blue":0.0,"Alpha":0.0},"Index":16,"UV":{"discriminator":"Elements.Geometry.UV","U":0.0,"V":0.0},"Id":0,"HalfEdge":null,"Point":{"X":0.0,"Y":0.0,"Z":0.0}},{"discriminator":"Elements.Geometry.Solids.Vertex","Position":{"X":-9.66509634997303,"Y":-25.973472041564793,"Z":0.39028878197218697},"Normal":{"X":0.0,"Y":0.0,"Z":1.0},"Color":{"Red":0.0,"Green":0.0,"Blue":0.0,"Alpha":0.0},"Index":17,"UV":{"discriminator":"Elements.Geometry.UV","U":0.0,"V":0.0},"Id":0,"HalfEdge":null,"Point":{"X":0.0,"Y":0.0,"Z":0.0}}],"Triangles":[{"discriminator":"Elements.Geometry.Triangle","Vertices":[{"discriminator":"Elements.Geometry.Solids.Vertex","Position":{"X":-8.3650963499731166,"Y":-25.973472041564793,"Z":0.39028878197218669},"Normal":{"X":0.0,"Y":0.0,"Z":1.0},"Color":{"Red":0.0,"Green":0.0,"Blue":0.0,"Alpha":0.0},"Index":0,"UV":{"discriminator":"Elements.Geometry.UV","U":0.0,"V":0.0},"Id":0,"HalfEdge":null,"Point":{"X":0.0,"Y":0.0,"Z":0.0}},{"discriminator":"Elements.Geometry.Solids.Vertex","Position":{"X":-2.465096349973078,"Y":-20.0734720415648,"Z":0.39028878197218669},"Normal":{"X":0.0,"Y":0.0,"Z":1.0},"Color":{"Red":0.0,"Green":0.0,"Blue":0.0,"Alpha":0.0},"Index":1,"UV":{"discriminator":"Elements.Geometry.UV","U":0.0,"V":0.0},"Id":0,"HalfEdge":null,"Point":{"X":0.0,"Y":0.0,"Z":0.0}},{"discriminator":"Elements.Geometry.Solids.Vertex","Position":{"X":-9.66509634997303,"Y":-25.973472041564793,"Z":0.39028878197218669},"Normal":{"X":0.0,"Y":0.0,"Z":1.0},"Color":{"Red":0.0,"Green":0.0,"Blue":0.0,"Alpha":0.0},"Index":2,"UV":{"discriminator":"Elements.Geometry.UV","U":0.0,"V":0.0},"Id":0,"HalfEdge":null,"Point":{"X":0.0,"Y":0.0,"Z":0.0}}],"Normal":{"X":0.0,"Y":0.0,"Z":1.0}},{"discriminator":"Elements.Geometry.Triangle","Vertices":[{"discriminator":"Elements.Geometry.Solids.Vertex","Position":{"X":-2.465096349973078,"Y":-20.0734720415648,"Z":0.39028878197218669},"Normal":{"X":0.0,"Y":0.0,"Z":1.0},"Color":{"Red":0.0,"Green":0.0,"Blue":0.0,"Alpha":0.0},"Index":3,"UV":{"discriminator":"Elements.Geometry.UV","U":0.0,"V":0.0},"Id":0,"HalfEdge":null,"Point":{"X":0.0,"Y":0.0,"Z":0.0}},{"discriminator":"Elements.Geometry.Solids.Vertex","Position":{"X":-15.56509634997308,"Y":-20.0734720415648,"Z":0.39028878197218669},"Normal":{"X":0.0,"Y":0.0,"Z":1.0},"Color":{"Red":0.0,"Green":0.0,"Blue":0.0,"Alpha":0.0},"Index":4,"UV":{"discriminator":"Elements.Geometry.UV","U":0.0,"V":0.0},"Id":0,"HalfEdge":null,"Point":{"X":0.0,"Y":0.0,"Z":0.0}},{"discriminator":"Elements.Geometry.Solids.Vertex","Position":{"X":-9.66509634997303,"Y":-25.973472041564793,"Z":0.39028878197218669},"Normal":{"X":0.0,"Y":0.0,"Z":1.0},"Color":{"Red":0.0,"Green":0.0,"Blue":0.0,"Alpha":0.0},"Index":5,"UV":{"discriminator":"Elements.Geometry.UV","U":0.0,"V":0.0},"Id":0,"HalfEdge":null,"Point":{"X":0.0,"Y":0.0,"Z":0.0}}],"Normal":{"X":0.0,"Y":0.0,"Z":1.0}},{"discriminator":"Elements.Geometry.Triangle","Vertices":[{"discriminator":"Elements.Geometry.Solids.Vertex","Position":{"X":-2.465096349973078,"Y":-31.8734720415648,"Z":0.39028878197218697},"Normal":{"X":0.0,"Y":0.0,"Z":1.0},"Color":{"Red":0.0,"Green":0.0,"Blue":0.0,"Alpha":0.0},"Index":6,"UV":{"discriminator":"Elements.Geometry.UV","U":0.0,"V":0.0},"Id":0,"HalfEdge":null,"Point":{"X":0.0,"Y":0.0,"Z":0.0}},{"discriminator":"Elements.Geometry.Solids.Vertex","Position":{"X":-2.465096349973078,"Y":-20.0734720415648,"Z":0.39028878197218697},"Normal":{"X":0.0,"Y":0.0,"Z":1.0},"Color":{"Red":0.0,"Green":0.0,"Blue":0.0,"Alpha":0.0},"Index":7,"UV":{"discriminator":"Elements.Geometry.UV","U":0.0,"V":0.0},"Id":0,"HalfEdge":null,"Point":{"X":0.0,"Y":0.0,"Z":0.0}},{"discriminator":"Elements.Geometry.Solids.Vertex","Position":{"X":-8.3650963499731166,"Y":-25.973472041564793,"Z":0.39028878197218697},"Normal":{"X":0.0,"Y":0.0,"Z":1.0},"Color":{"Red":0.0,"Green":0.0,"Blue":0.0,"Alpha":0.0},"Index":8,"UV":{"discriminator":"Elements.Geometry.UV","U":0.0,"V":0.0},"Id":0,"HalfEdge":null,"Point":{"X":0.0,"Y":0.0,"Z":0.0}}],"Normal":{"X":0.0,"Y":0.0,"Z":1.0}},{"discriminator":"Elements.Geometry.Triangle","Vertices":[{"discriminator":"Elements.Geometry.Solids.Vertex","Position":{"X":-2.465096349973078,"Y":-31.8734720415648,"Z":0.39028878197218697},"Normal":{"X":0.0,"Y":0.0,"Z":1.0},"Color":{"Red":0.0,"Green":0.0,"Blue":0.0,"Alpha":0.0},"Index":9,"UV":{"discriminator":"Elements.Geometry.UV","U":0.0,"V":0.0},"Id":0,"HalfEdge":null,"Point":{"X":0.0,"Y":0.0,"Z":0.0}},{"discriminator":"Elements.Geometry.Solids.Vertex","Position":{"X":-8.3650963499731166,"Y":-25.973472041564793,"Z":0.39028878197218697},"Normal":{"X":0.0,"Y":0.0,"Z":1.0},"Color":{"Red":0.0,"Green":0.0,"Blue":0.0,"Alpha":0.0},"Index":10,"UV":{"discriminator":"Elements.Geometry.UV","U":0.0,"V":0.0},"Id":0,"HalfEdge":null,"Point":{"X":0.0,"Y":0.0,"Z":0.0}},{"discriminator":"Elements.Geometry.Solids.Vertex","Position":{"X":-9.66509634997303,"Y":-25.973472041564793,"Z":0.39028878197218697},"Normal":{"X":0.0,"Y":0.0,"Z":1.0},"Color":{"Red":0.0,"Green":0.0,"Blue":0.0,"Alpha":0.0},"Index":11,"UV":{"discriminator":"Elements.Geometry.UV","U":0.0,"V":0.0},"Id":0,"HalfEdge":null,"Point":{"X":0.0,"Y":0.0,"Z":0.0}}],"Normal":{"X":0.0,"Y":0.0,"Z":1.0}},{"discriminator":"Elements.Geometry.Triangle","Vertices":[{"discriminator":"Elements.Geometry.Solids.Vertex","Position":{"X":-9.66509634997303,"Y":-25.973472041564793,"Z":0.39028878197218697},"Normal":{"X":0.0,"Y":0.0,"Z":1.0},"Color":{"Red":0.0,"Green":0.0,"Blue":0.0,"Alpha":0.0},"Index":12,"UV":{"discriminator":"Elements.Geometry.UV","U":0.0,"V":0.0},"Id":0,"HalfEdge":null,"Point":{"X":0.0,"Y":0.0,"Z":0.0}},{"discriminator":"Elements.Geometry.Solids.Vertex","Position":{"X":-15.56509634997308,"Y":-31.8734720415648,"Z":0.39028878197218697},"Normal":{"X":0.0,"Y":0.0,"Z":1.0},"Color":{"Red":0.0,"Green":0.0,"Blue":0.0,"Alpha":0.0},"Index":13,"UV":{"discriminator":"Elements.Geometry.UV","U":0.0,"V":0.0},"Id":0,"HalfEdge":null,"Point":{"X":0.0,"Y":0.0,"Z":0.0}},{"discriminator":"Elements.Geometry.Solids.Vertex","Position":{"X":-2.465096349973078,"Y":-31.8734720415648,"Z":0.39028878197218697},"Normal":{"X":0.0,"Y":0.0,"Z":1.0},"Color":{"Red":0.0,"Green":0.0,"Blue":0.0,"Alpha":0.0},"Index":14,"UV":{"discriminator":"Elements.Geometry.UV","U":0.0,"V":0.0},"Id":0,"HalfEdge":null,"Point":{"X":0.0,"Y":0.0,"Z":0.0}}],"Normal":{"X":0.0,"Y":0.0,"Z":1.0}},{"discriminator":"Elements.Geometry.Triangle","Vertices":[{"discriminator":"Elements.Geometry.Solids.Vertex","Position":{"X":-15.56509634997308,"Y":-20.0734720415648,"Z":0.39028878197218697},"Normal":{"X":0.0,"Y":0.0,"Z":1.0},"Color":{"Red":0.0,"Green":0.0,"Blue":0.0,"Alpha":0.0},"Index":15,"UV":{"discriminator":"Elements.Geometry.UV","U":0.0,"V":0.0},"Id":0,"HalfEdge":null,"Point":{"X":0.0,"Y":0.0,"Z":0.0}},{"discriminator":"Elements.Geometry.Solids.Vertex","Position":{"X":-15.56509634997308,"Y":-31.8734720415648,"Z":0.39028878197218697},"Normal":{"X":0.0,"Y":0.0,"Z":1.0},"Color":{"Red":0.0,"Green":0.0,"Blue":0.0,"Alpha":0.0},"Index":16,"UV":{"discriminator":"Elements.Geometry.UV","U":0.0,"V":0.0},"Id":0,"HalfEdge":null,"Point":{"X":0.0,"Y":0.0,"Z":0.0}},{"discriminator":"Elements.Geometry.Solids.Vertex","Position":{"X":-9.66509634997303,"Y":-25.973472041564793,"Z":0.39028878197218697},"Normal":{"X":0.0,"Y":0.0,"Z":1.0},"Color":{"Red":0.0,"Green":0.0,"Blue":0.0,"Alpha":0.0},"Index":17,"UV":{"discriminator":"Elements.Geometry.UV","U":0.0,"V":0.0},"Id":0,"HalfEdge":null,"Point":{"X":0.0,"Y":0.0,"Z":0.0}}],"Normal":{"X":0.0,"Y":0.0,"Z":1.0}}],"Material":"9babb829-9b96-4e73-97f4-9658d4d6c31c"},"Underside":{"discriminator":"Mesh","Vertices":[],"Triangles":[],"Material":"9babb829-9b96-4e73-97f4-9658d4d6c31c"},"Perimeter":{"discriminator":"Elements.Geometry.Polygon","Vertices":[{"X":-15.56509634997308,"Y":-20.0734720415648,"Z":0.0},{"X":-15.56509634997308,"Y":-31.8734720415648,"Z":0.0},{"X":-2.465096349973078,"Y":-31.8734720415648,"Z":0.0},{"X":-2.465096349973078,"Y":-20.0734720415648,"Z":0.0}]},"Elevation":0.0,"Highpoint":3.7966553701909977,"Thickness":0.338,"Area":585.60895414260119,"Transform":{"Matrix":{"Components":[1.0,0.0,0.0,0.0,0.0,1.0,0.0,0.0,0.0,0.0,1.0,0.0]}},"Material":"7298d643-9049-4a2b-960d-ae775b50fd80","Representation":null,"IsElementDefinition":false,"Id":"07cd4e72-d669-4648-b681-cc6ee125ac5f","Name":"Roof"}}}